{"current_re": ["master", "fpc0", "node", "fwdd", "member", "pfem", "re0", "fpc0.pic0"], "domain": "cisco.com", "fqdn": "srx01.cisco.com", "switch_style": "NONE", "HOME": "/var/home/cisco", "srx_cluster": false, "srx_cluster_id": null, "srx_cluster_redundancy_group": null, "RE_hw_mi": false, "serialnumber": "195e9fee66fa", "master": "RE0", "RE0": {"mastership_state": "master", "status": "Testing", "model": "VSRX RE", "last_reboot_reason": "Router rebooted after a normal shutdown.", "up_time": "16 hours, 5 minutes, 15 seconds"}, "RE1": null, "re_info": {"default": {"0": {"mastership_state": "master", "status": "Testing", "model": "VSRX RE", "last_reboot_reason": "Router rebooted after a normal shutdown."}, "default": {"mastership_state": "master", "status": "Testing", "model": "VSRX RE", "last_reboot_reason": "Router rebooted after a normal shutdown."}}}, "re_master": {"default": "0"}, "junos_info": {"re0": {"text": "20.1R1.11", "object": {"major": [20, 1], "type": "R", "minor": "1", "build": 11}}}, "hostname": "srx01", "hostname_info": {"re0": "srx01"}, "model": "VSRX", "model_info": {"re0": "VSRX"}, "version": "20.1R1.11", "version_info": {"major": [20, 1], "type": "R", "minor": "1", "build": 11}, "version_RE0": "20.1R1.11", "version_RE1": null, "vc_capable": false, "vc_mode": null, "vc_fabric": null, "vc_master": null, "ifd_style": "CLASSIC", "personality": null, "virtual": null, "re_name": "re0", "master_state": true, "has_2RE": false}